README.md
setup.py
subtokenizer/__init__.py
subtokenizer/__main__.py
subtokenizer/subtokenizer.py
subtokenizer/subwords.py
subtokenizer/tokenizer.py
subtokenizer/utils.py
subtokenizer.egg-info/PKG-INFO
subtokenizer.egg-info/SOURCES.txt
subtokenizer.egg-info/dependency_links.txt
subtokenizer.egg-info/entry_points.txt
subtokenizer.egg-info/requires.txt
subtokenizer.egg-info/top_level.txt