Metadata-Version: 1.2
Name: subtokenizer
Version: 0.0.12
Summary: Subwords tokenizer for neural natural language processing
Home-page: https://github.com/kovalevfm/SubTokenizer
Author: Fedor Kovalev
Author-email: kovalevfm@gmail.com
License: MIT
Keywords: nlp tokenization
Platform: UNKNOWN
Requires-Python: >=2.6, <4.0
